seokbong_add/__init__.py
seokbong_add/add.py
seokbong_add-1.0.0.dist-info/METADATA
seokbong_add-1.0.0.dist-info/WHEEL
seokbong_add-1.0.0.dist-info/entry_points.txt
seokbong_add-1.0.0.dist-info/top_level.txt
seokbong_add-1.0.0.dist-info/RECORD
