Metadata-Version: 2.1
Name: seokbong_add
Version: 1.0.0
Summary: Default template for PDM package
Author-email: Seokxkyu <kyuseok000@gmail.com>
License: MIT
Requires-Python: >=3.9
